apiflash/__init__.py
apiflash-0.1.4.dist-info/LICENSE
apiflash-0.1.4.dist-info/METADATA
apiflash-0.1.4.dist-info/WHEEL
apiflash-0.1.4.dist-info/top_level.txt
apiflash-0.1.4.dist-info/RECORD
